xchat/__init__.py
xchat/utils.py
xchat/itchat/__init__.py
xchat/itchat/config.py
xchat/itchat/content.py
xchat/itchat/core.py
xchat/itchat/log.py
xchat/itchat/returnvalues.py
xchat/itchat/utils.py
xchat/itchat/async_components/__init__.py
xchat/itchat/async_components/contact.py
xchat/itchat/async_components/hotreload.py
xchat/itchat/async_components/login.py
xchat/itchat/async_components/messages.py
xchat/itchat/async_components/register.py
xchat/itchat/components/__init__.py
xchat/itchat/components/contact.py
xchat/itchat/components/hotreload.py
xchat/itchat/components/login.py
xchat/itchat/components/messages.py
xchat/itchat/components/register.py
xchat/itchat/storage/__init__.py
xchat/itchat/storage/messagequeue.py
xchat/itchat/storage/templates.py
xchat/openai/__init__.py
xchat/openai/_openai_scripts.py
xchat/openai/api_requestor.py
xchat/openai/cli.py
xchat/openai/embeddings_utils.py
xchat/openai/error.py
xchat/openai/object_classes.py
xchat/openai/openai_object.py
xchat/openai/openai_response.py
xchat/openai/upload_progress.py
xchat/openai/util.py
xchat/openai/validators.py
xchat/openai/version.py
xchat/openai/wandb_logger.py
xchat/openai/api_resources/__init__.py
xchat/openai/api_resources/audio.py
xchat/openai/api_resources/chat_completion.py
xchat/openai/api_resources/completion.py
xchat/openai/api_resources/customer.py
xchat/openai/api_resources/deployment.py
xchat/openai/api_resources/edit.py
xchat/openai/api_resources/embedding.py
xchat/openai/api_resources/engine.py
xchat/openai/api_resources/error_object.py
xchat/openai/api_resources/file.py
xchat/openai/api_resources/fine_tune.py
xchat/openai/api_resources/fine_tuning.py
xchat/openai/api_resources/image.py
xchat/openai/api_resources/model.py
xchat/openai/api_resources/moderation.py
xchat/openai/api_resources/abstract/__init__.py
xchat/openai/api_resources/abstract/api_resource.py
xchat/openai/api_resources/abstract/createable_api_resource.py
xchat-2023.11.16.17.50.4.dist-info/LICENSE
xchat-2023.11.16.17.50.4.dist-info/METADATA
xchat-2023.11.16.17.50.4.dist-info/WHEEL
xchat-2023.11.16.17.50.4.dist-info/entry_points.txt
xchat-2023.11.16.17.50.4.dist-info/top_level.txt
xchat-2023.11.16.17.50.4.dist-info/RECORD
