Metadata-Version: 2.1
Name: xchat
Version: 2023.11.16.17.50.4
Summary: xchat
Home-page: https://github.com/yuanjie-ai/xchat
Author: xchat
Author-email: yuanjie@example.com
License: MIT license
Keywords: xchat
Classifier: Development Status :: 2 - Pre-Alpha
Classifier: Intended Audience :: Developers
Classifier: License :: OSI Approved :: MIT License
Classifier: Natural Language :: English
Classifier: Programming Language :: Python :: 3
Classifier: Programming Language :: Python :: 3.6
Classifier: Programming Language :: Python :: 3.7
Classifier: Programming Language :: Python :: 3.8
Requires-Python: >=3.6
License-File: LICENSE
Requires-Dist: meutils
Requires-Dist: pyppeteer
Requires-Dist: dataclasses-json
Requires-Dist: pyee
Requires-Dist: PyQRCode
Requires-Dist: grpclib
Requires-Dist: node-semver (~=0.8.1)
